LICENSE
MANIFEST.in
README.md
forwardable.py
setup.py
forwardable.py.egg-info/PKG-INFO
forwardable.py.egg-info/SOURCES.txt
forwardable.py.egg-info/dependency_links.txt
forwardable.py.egg-info/top_level.txt