Metadata-Version: 1.1
Name: forwardable.py
Version: 0.0.11
Summary: pythoniac port forwardable from Ruby
Home-page: https://github.com/hachibeeDI/forwardable.py
Author: OGURA_Daiki
Author-email: 8hachibee125@gmail.com
License: The MIT License (MIT)
